jzp/__init__.py
jzp/cli.py
jzp/header.py
jzp-0.0.2.dist-info/METADATA
jzp-0.0.2.dist-info/WHEEL
jzp-0.0.2.dist-info/entry_points.txt
jzp-0.0.2.dist-info/RECORD
