Metadata-Version: 2.4
Name: jzp
Version: 0.0.2
Summary: A libary for dealing with the compression and decompression of Agilent JZP files.
Project-URL: Source Code, https://github.com/antoniovazquezblanco/jzp/
Project-URL: Issue Tracker, https://github.com/antoniovazquezblanco/jzp/issues
Author-email: Antonio Vázquez <antoniovazquezblanco@gmail.com>
Maintainer-email: Antonio Vázquez <antoniovazquezblanco@gmail.com>
License: GPL-3.0-or-later
Classifier: Development Status :: 4 - Beta
Classifier: License :: OSI Approved :: GNU General Public License v3 or later (GPLv3+)
Classifier: Operating System :: OS Independent
Classifier: Programming Language :: Python
Requires-Python: >=3.7
Requires-Dist: lzsslib>=0.0.2
